src/__init__.py
src/backend.py
src/business.py
src/main.py
src/utils.py
azdiff-0.1.dist-info/METADATA
azdiff-0.1.dist-info/WHEEL
azdiff-0.1.dist-info/entry_points.txt
azdiff-0.1.dist-info/top_level.txt
azdiff-0.1.dist-info/RECORD
