Metadata-Version: 2.1
Name: azdiff
Version: 0.1
Summary: Azure resources configuration differences
Home-page: https://github.com/RachidAZ/AzDiff
Author: Rachid Azgaou
Author-email: rachid.azgaou.us@gmail.com
Classifier: Programming Language :: Python :: 3
Classifier: License :: OSI Approved :: MIT License
Classifier: Operating System :: OS Independent
Requires-Python: >=3.8
Requires-Dist: azure-mgmt-resource ==23.0.1
Requires-Dist: azure-mgmt-web ==7.2.0
Requires-Dist: azure-mgmt-compute ==30.4.0
Requires-Dist: azure-identity ==1.5.0
Requires-Dist: tabulate ==0.9.0
Requires-Dist: click
